MANIFEST.in
README.rst
setup.py
src/lxtokenizer/__init__.py
src/lxtokenizer/__main__.py
src/lxtokenizer/lxtokenizer.py
src/lxtokenizer/lxtokenizer2.py
src/lxtokenizer.egg-info/PKG-INFO
src/lxtokenizer.egg-info/SOURCES.txt
src/lxtokenizer.egg-info/dependency_links.txt
src/lxtokenizer.egg-info/entry_points.txt
src/lxtokenizer.egg-info/requires.txt
src/lxtokenizer.egg-info/top_level.txt
src/lxtokenizer/tokenizer/Makefile
src/lxtokenizer/tokenizer/abbrevs.txt
src/lxtokenizer/tokenizer/avlt.c
src/lxtokenizer/tokenizer/avlt.h
src/lxtokenizer/tokenizer/clitics.txt
src/lxtokenizer/tokenizer/contrs.txt
src/lxtokenizer/tokenizer/tokenizer.lex
src/lxtokenizer/tokenizer/i686/tokenizer
src/lxtokenizer/tokenizer/x86_64/tokenizer